{"errors":[],"sptypes":[{"ann":"GHC.Types.Module","ident":"LHExercises.$trModule","start":{"column":1,"line":1},"stop":{"column":1,"line":1}},{"ann":"forall a . x1:[a] -> {VV : GHC.Types.Int | VV == realSize x1}","ident":"LHExercises.realSize","start":{"column":1,"line":40},"stop":{"column":9,"line":40}},{"ann":"{v : GHC.Prim.Int# | v == 0}","ident":"lq_anf$##7205759403793234484","start":{"column":19,"line":40},"stop":{"column":20,"line":40}},{"ann":"GHC.Types.Int","ident":"lq_anf$##7205759403793234486","start":{"column":19,"line":41},"stop":{"column":20,"line":41}},{"ann":"{v : GHC.Types.Int | v == realSize xs}","ident":"lq_anf$##7205759403793234487","start":{"column":23,"line":41},"stop":{"column":34,"line":41}},{"ann":"{v : [a] | v == xs\n           && len v >= 0}","ident":"xs","start":{"column":32,"line":41},"stop":{"column":34,"line":41}},{"ann":"forall a . {VV : (LHExercises.SList a) | size VV == 0}","ident":"LHExercises.nil","start":{"column":1,"line":59},"stop":{"column":4,"line":59}},{"ann":"GHC.Types.Int","ident":"lq_anf$##7205759403793234489","start":{"column":23,"line":59},"stop":{"column":24,"line":59}},{"ann":"{VV : forall a <p :: a a -> Bool>.\n      {v : [a]<\\x3 VV -> {VV : a<p x3> | true}> | len v == 0\n                                                  && realSize v == 0} | VV == []}","ident":"_","start":{"column":25,"line":59},"stop":{"column":27,"line":59}},{"ann":"forall a .\na -> x2:(LHExercises.SList a) -> {VV : (LHExercises.SList a) | size VV == size x2 + 1}","ident":"LHExercises.cons","start":{"column":1,"line":63},"stop":{"column":5,"line":63}},{"ann":"a","ident":"x","start":{"column":6,"line":63},"stop":{"column":7,"line":63}},{"ann":"{VV : forall a .\n      x1:{v : GHC.Types.Int | v >= 0} -> x2:{v : [a] | realSize v == x1} -> {v : (LHExercises.SList a) | elems v == x2\n                                                                                                         && size v == x1} | VV == SL}","ident":"LHExercises.SL","start":{"column":20,"line":63},"stop":{"column":35,"line":63}},{"ann":"GHC.Types.Int","ident":"lq_anf$##7205759403793234498","start":{"column":23,"line":63},"stop":{"column":28,"line":63}},{"ann":"{v : GHC.Types.Int | v == n\n                     && v >= 0}","ident":"n","start":{"column":24,"line":63},"stop":{"column":25,"line":63}},{"ann":"GHC.Types.Int","ident":"lq_anf$##7205759403793234497","start":{"column":26,"line":63},"stop":{"column":27,"line":63}},{"ann":"{v : [a] | head v == x\n           && len v == 1 + len xs\n           && realSize v == 1 + realSize xs\n           && tail v == xs}","ident":"lq_anf$##7205759403793234499","start":{"column":29,"line":63},"stop":{"column":35,"line":63}},{"ann":"{VV : a | VV == x}","ident":"x","start":{"column":30,"line":63},"stop":{"column":31,"line":63}},{"ann":"{v : [a] | v == xs\n           && realSize v == n\n           && len v >= 0}","ident":"xs","start":{"column":32,"line":63},"stop":{"column":34,"line":63}},{"ann":"forall a .\nx1:{VV : (LHExercises.SList a) | size VV > 0} -> {VV : (LHExercises.SList a) | size VV == size x1 - 1}","ident":"LHExercises.tl","start":{"column":1,"line":68},"stop":{"column":3,"line":68}},{"ann":"{VV : forall a .\n      x1:{v : GHC.Types.Int | v >= 0} -> x2:{v : [a] | realSize v == x1} -> {v : (LHExercises.SList a) | elems v == x2\n                                                                                                         && size v == x1} | VV == SL}","ident":"LHExercises.SL","start":{"column":20,"line":68},"stop":{"column":31,"line":68}},{"ann":"GHC.Types.Int","ident":"lq_anf$##7205759403793234513","start":{"column":23,"line":68},"stop":{"column":28,"line":68}},{"ann":"{v : GHC.Types.Int | v == n\n                     && v >= 0}","ident":"n","start":{"column":24,"line":68},"stop":{"column":25,"line":68}},{"ann":"GHC.Types.Int","ident":"lq_anf$##7205759403793234512","start":{"column":26,"line":68},"stop":{"column":27,"line":68}},{"ann":"{v : [a] | v == xs\n           && len v >= 0}","ident":"xs","start":{"column":29,"line":68},"stop":{"column":31,"line":68}},{"ann":"forall a . {VV : (LHExercises.SList a) | size VV > 0} -> a","ident":"LHExercises.hd","start":{"column":1,"line":71},"stop":{"column":3,"line":71}},{"ann":"{VV : a | VV == x}","ident":"x","start":{"column":20,"line":71},"stop":{"column":21,"line":71}},{"ann":"forall a .\nx1:(LHExercises.Queue a) -> {VV : GHC.Types.Int | VV == qsize x1}","ident":"LHExercises.qsize","start":{"column":1,"line":88},"stop":{"column":6,"line":88}},{"ann":"{v : GHC.Types.Int | v == size f\n                     && v >= 0}","ident":"lq_anf$##7205759403793234553","start":{"column":17,"line":88},"stop":{"column":23,"line":88}},{"ann":"{v : (LHExercises.SList a) | v == f}","ident":"f","start":{"column":22,"line":88},"stop":{"column":23,"line":88}},{"ann":"{v : GHC.Types.Int | v == size b\n                     && v >= 0}","ident":"lq_anf$##7205759403793234554","start":{"column":26,"line":88},"stop":{"column":32,"line":88}},{"ann":"{v : (LHExercises.SList a) | v == b\n                             && size v <= size f}","ident":"b","start":{"column":31,"line":88},"stop":{"column":32,"line":88}},{"ann":"forall a .\nx1:(LHExercises.SList a) -> x2:{VV : (LHExercises.SList a) | size VV <= size x1 + 1} -> {VV : (LHExercises.Queue a) | qsize VV == size x1 + size x2}","ident":"LHExercises.makeq","start":{"column":1,"line":98},"stop":{"column":6,"line":98}},{"ann":"(LHExercises.SList a)","ident":"f","start":{"column":7,"line":98},"stop":{"column":8,"line":98}},{"ann":"{VV : (LHExercises.SList a) | size VV <= size f + 1}","ident":"b","start":{"column":9,"line":98},"stop":{"column":10,"line":98}},{"ann":"{v : GHC.Types.Int | v == size b\n                     && v >= 0}","ident":"lq_anf$##7205759403793234531","start":{"column":5,"line":99},"stop":{"column":11,"line":99}},{"ann":"{v : (LHExercises.SList a) | v == b\n                             && size v <= size f + 1}","ident":"b","start":{"column":10,"line":99},"stop":{"column":11,"line":99}},{"ann":"{v : GHC.Types.Int | v == size f\n                     && v >= 0}","ident":"lq_anf$##7205759403793234532","start":{"column":15,"line":99},"stop":{"column":21,"line":99}},{"ann":"{v : (LHExercises.SList a) | v == f}","ident":"f","start":{"column":20,"line":99},"stop":{"column":21,"line":99}},{"ann":"{VV : forall a .\n      x1:(LHExercises.SList a) -> x2:{v : (LHExercises.SList a) | size v <= size x1} -> {v : (LHExercises.Queue a) | back v == x2\n                                                                                                                     && front v == x1\n                                                                                                                     && qsize v == size x1 + size x2} | VV == Q}","ident":"LHExercises.Q","start":{"column":24,"line":99},"stop":{"column":29,"line":99}},{"ann":"{v : (LHExercises.SList a) | v == f}","ident":"f","start":{"column":26,"line":99},"stop":{"column":27,"line":99}},{"ann":"{v : (LHExercises.SList a) | v == b\n                             && size v <= size f + 1}","ident":"b","start":{"column":28,"line":99},"stop":{"column":29,"line":99}},{"ann":"{v : (LHExercises.SList a) | size v == 0}","ident":"lq_anf$##7205759403793234537","start":{"column":17,"line":100},"stop":{"column":36,"line":100}},{"ann":"(LHExercises.SList a)","ident":"lq_anf$##7205759403793234536","start":{"column":19,"line":100},"stop":{"column":32,"line":100}},{"ann":"{v : (LHExercises.SList a) | v == f}","ident":"f","start":{"column":24,"line":100},"stop":{"column":25,"line":100}},{"ann":"{v : (LHExercises.SList a) | v == b\n                             && size v <= size f + 1}","ident":"b","start":{"column":26,"line":100},"stop":{"column":27,"line":100}},{"ann":"{VV : forall a .\n      {v : (LHExercises.SList a) | size v == 0} | VV == nil}","ident":"_","start":{"column":28,"line":100},"stop":{"column":31,"line":100}},{"ann":"{VV : forall a .\n      {v : (LHExercises.SList a) | size v == 0} | VV == nil}","ident":"_","start":{"column":33,"line":100},"stop":{"column":36,"line":100}},{"ann":"forall a .\nx1:(LHExercises.SList a) -> x2:{VV : (LHExercises.SList a) | size VV == size x1 + 1} -> x3:(LHExercises.SList a) -> {v : (LHExercises.SList a) | size v == (size x1 + size x2) + size x3}","ident":"LHExercises.rot","start":{"column":1,"line":103},"stop":{"column":4,"line":103}},{"ann":"(LHExercises.SList a)","ident":"f","start":{"column":5,"line":103},"stop":{"column":6,"line":103}},{"ann":"{VV : (LHExercises.SList a) | size VV == size f + 1}","ident":"b","start":{"column":7,"line":103},"stop":{"column":8,"line":103}},{"ann":"(LHExercises.SList a)","ident":"acc","start":{"column":9,"line":103},"stop":{"column":12,"line":103}},{"ann":"{v : GHC.Types.Int | v == size f\n                     && v >= 0}","ident":"lq_anf$##7205759403793234519","start":{"column":5,"line":104},"stop":{"column":11,"line":104}},{"ann":"{v : (LHExercises.SList a) | v == f}","ident":"f","start":{"column":10,"line":104},"stop":{"column":11,"line":104}},{"ann":"GHC.Types.Int","ident":"lq_anf$##7205759403793234521","start":{"column":15,"line":104},"stop":{"column":16,"line":104}},{"ann":"a","ident":"lq_anf$##7205759403793234530","start":{"column":19,"line":104},"stop":{"column":23,"line":104}},{"ann":"{v : (LHExercises.SList a) | v == b\n                             && size v == size f + 1}","ident":"b","start":{"column":22,"line":104},"stop":{"column":23,"line":104}},{"ann":"{v : (LHExercises.SList a) | v == acc}","ident":"acc","start":{"column":31,"line":104},"stop":{"column":34,"line":104}},{"ann":"a","ident":"lq_anf$##7205759403793234524","start":{"column":17,"line":105},"stop":{"column":21,"line":105}},{"ann":"{v : (LHExercises.SList a) | v == f}","ident":"f","start":{"column":20,"line":105},"stop":{"column":21,"line":105}},{"ann":"(LHExercises.SList a)","ident":"lq_anf$##7205759403793234529","start":{"column":29,"line":105},"stop":{"column":64,"line":105}},{"ann":"{v : (LHExercises.SList a) | size v == size f - 1}","ident":"lq_anf$##7205759403793234525","start":{"column":33,"line":105},"stop":{"column":39,"line":105}},{"ann":"{v : (LHExercises.SList a) | v == f}","ident":"f","start":{"column":37,"line":105},"stop":{"column":38,"line":105}},{"ann":"{v : (LHExercises.SList a) | size v == size b - 1}","ident":"lq_anf$##7205759403793234526","start":{"column":40,"line":105},"stop":{"column":46,"line":105}},{"ann":"{v : (LHExercises.SList a) | v == b\n                             && size v == size f + 1}","ident":"b","start":{"column":44,"line":105},"stop":{"column":45,"line":105}},{"ann":"{v : (LHExercises.SList a) | size v == size acc + 1}","ident":"lq_anf$##7205759403793234528","start":{"column":47,"line":105},"stop":{"column":64,"line":105}},{"ann":"a","ident":"lq_anf$##7205759403793234527","start":{"column":48,"line":105},"stop":{"column":52,"line":105}},{"ann":"{v : (LHExercises.SList a) | v == b\n                             && size v == size f + 1}","ident":"b","start":{"column":51,"line":105},"stop":{"column":52,"line":105}},{"ann":"{v : (LHExercises.SList a) | v == acc}","ident":"acc","start":{"column":60,"line":105},"stop":{"column":63,"line":105}},{"ann":"forall a .\nx1:(LHExercises.Queue a) -> {mq : (GHC.Maybe.Maybe {VV : (LHExercises.Queue a) | qsize VV == qsize x1 - 1}) | qsize x1 > 0 => isJust mq}","ident":"LHExercises.remove","start":{"column":1,"line":111},"stop":{"column":7,"line":111}},{"ann":"(LHExercises.Queue a)","ident":"qi","start":{"column":8,"line":111},"stop":{"column":10,"line":111}},{"ann":"{v : GHC.Types.Int | v == size f\n                     && v >= 0}","ident":"lq_anf$##7205759403793234539","start":{"column":5,"line":112},"stop":{"column":11,"line":112}},{"ann":"{v : (LHExercises.SList a) | v == f}","ident":"f","start":{"column":10,"line":112},"stop":{"column":11,"line":112}},{"ann":"GHC.Types.Int","ident":"lq_anf$##7205759403793234541","start":{"column":15,"line":112},"stop":{"column":16,"line":112}},{"ann":"{v : GHC.Types.Int | v == size b\n                     && v >= 0}","ident":"lq_anf$##7205759403793234543","start":{"column":20,"line":112},"stop":{"column":26,"line":112}},{"ann":"{v : (LHExercises.SList a) | v == b\n                             && size v <= size f}","ident":"b","start":{"column":25,"line":112},"stop":{"column":26,"line":112}},{"ann":"GHC.Types.Int","ident":"lq_anf$##7205759403793234545","start":{"column":30,"line":112},"stop":{"column":31,"line":112}},{"ann":"{VV : forall a .\n      {v : (GHC.Maybe.Maybe a) | not (isJust v)} | VV == Nothing}","ident":"_","start":{"column":34,"line":112},"stop":{"column":41,"line":112}},{"ann":"{VV : forall a .\n      x1:a -> {v : (GHC.Maybe.Maybe a) | isJust v\n                                         && fromJust v == x1\n                                         && lqdc##$select v == x1} | VV == Just}","ident":"GHC.Maybe.Just","start":{"column":17,"line":113},"stop":{"column":38,"line":113}},{"ann":"(LHExercises.Queue a)","ident":"lq_anf$##7205759403793234550","start":{"column":22,"line":113},"stop":{"column":38,"line":113}},{"ann":"{v : (LHExercises.SList a) | size v == size f - 1}","ident":"lq_anf$##7205759403793234549","start":{"column":29,"line":113},"stop":{"column":35,"line":113}},{"ann":"{v : (LHExercises.SList a) | v == f}","ident":"f","start":{"column":33,"line":113},"stop":{"column":34,"line":113}},{"ann":"{v : (LHExercises.SList a) | v == b\n                             && size v <= size f}","ident":"b","start":{"column":36,"line":113},"stop":{"column":37,"line":113}},{"ann":"(GHC.Maybe.Maybe (LHExercises.Queue GHC.Num.Integer.Integer))","ident":"LHExercises.okRemove","start":{"column":1,"line":118},"stop":{"column":9,"line":118}},{"ann":"{v : (LHExercises.Queue GHC.Num.Integer.Integer) | v == example2Q\n                                                   && qsize v == 2}","ident":"LHExercises.example2Q","start":{"column":19,"line":118},"stop":{"column":28,"line":118}},{"ann":"forall a . (GHC.Maybe.Maybe (LHExercises.Queue a))","ident":"LHExercises.badRemove","start":{"column":1,"line":120},"stop":{"column":10,"line":120}},{"ann":"{VV : forall a .\n      {v : (LHExercises.Queue a) | qsize v == 0} | VV == example0Q}","ident":"_","start":{"column":20,"line":120},"stop":{"column":29,"line":120}},{"ann":"forall a . {VV : (LHExercises.Queue a) | qsize VV == 0}","ident":"LHExercises.emp","start":{"column":1,"line":123},"stop":{"column":4,"line":123}},{"ann":"{VV : forall a .\n      {v : (LHExercises.SList a) | size v == 0} | VV == nil}","ident":"_","start":{"column":9,"line":123},"stop":{"column":12,"line":123}},{"ann":"{VV : forall a .\n      {v : (LHExercises.SList a) | size v == 0} | VV == nil}","ident":"_","start":{"column":13,"line":123},"stop":{"column":16,"line":123}},{"ann":"{VV : (LHExercises.Queue GHC.Num.Integer.Integer) | qsize VV == 2}","ident":"LHExercises.example2Q","start":{"column":1,"line":126},"stop":{"column":10,"line":126}},{"ann":"(LHExercises.SList GHC.Num.Integer.Integer)","ident":"lq_anf$##7205759403793234504","start":{"column":15,"line":126},"stop":{"column":40,"line":126}},{"ann":"{v : GHC.Num.Integer.Integer | v == 1}","ident":"lq_anf$##7205759403793234500","start":{"column":16,"line":126},"stop":{"column":17,"line":126}},{"ann":"(LHExercises.SList GHC.Num.Integer.Integer)","ident":"lq_anf$##7205759403793234503","start":{"column":25,"line":126},"stop":{"column":39,"line":126}},{"ann":"{v : GHC.Num.Integer.Integer | v == 2}","ident":"lq_anf$##7205759403793234501","start":{"column":26,"line":126},"stop":{"column":27,"line":126}},{"ann":"{VV : forall a .\n      {v : (LHExercises.SList a) | size v == 0} | VV == nil}","ident":"_","start":{"column":35,"line":126},"stop":{"column":38,"line":126}},{"ann":"{VV : forall a .\n      {v : (LHExercises.SList a) | size v == 0} | VV == nil}","ident":"_","start":{"column":41,"line":126},"stop":{"column":44,"line":126}},{"ann":"forall a . {VV : (LHExercises.Queue a) | qsize VV == 0}","ident":"LHExercises.example0Q","start":{"column":1,"line":129},"stop":{"column":10,"line":129}},{"ann":"{VV : forall a .\n      {v : (LHExercises.SList a) | size v == 0} | VV == nil}","ident":"_","start":{"column":15,"line":129},"stop":{"column":18,"line":129}},{"ann":"{VV : forall a .\n      {v : (LHExercises.SList a) | size v == 0} | VV == nil}","ident":"_","start":{"column":19,"line":129},"stop":{"column":22,"line":129}}],"status":"safe","types":{"1":{"1":{"ann":"GHC.Types.Module","col":1,"ident":"LHExercises.$trModule","row":1}},"100":{"17":{"ann":"{v : (LHExercises.SList a) | size v == 0}","col":17,"ident":"lq_anf$##7205759403793234537","row":100},"19":{"ann":"(LHExercises.SList a)","col":19,"ident":"lq_anf$##7205759403793234536","row":100},"24":{"ann":"{v : (LHExercises.SList a) | v == f}","col":24,"ident":"f","row":100},"26":{"ann":"{v : (LHExercises.SList a) | v == b\n                             && size v <= size f + 1}","col":26,"ident":"b","row":100},"28":{"ann":"{VV : forall a .\n      {v : (LHExercises.SList a) | size v == 0} | VV == nil}","col":28,"ident":"_","row":100},"33":{"ann":"{VV : forall a .\n      {v : (LHExercises.SList a) | size v == 0} | VV == nil}","col":33,"ident":"_","row":100}},"103":{"1":{"ann":"forall a .\nx1:(LHExercises.SList a) -> x2:{VV : (LHExercises.SList a) | size VV == size x1 + 1} -> x3:(LHExercises.SList a) -> {v : (LHExercises.SList a) | size v == (size x1 + size x2) + size x3}","col":1,"ident":"LHExercises.rot","row":103},"5":{"ann":"(LHExercises.SList a)","col":5,"ident":"f","row":103},"7":{"ann":"{VV : (LHExercises.SList a) | size VV == size f + 1}","col":7,"ident":"b","row":103},"9":{"ann":"(LHExercises.SList a)","col":9,"ident":"acc","row":103}},"104":{"10":{"ann":"{v : (LHExercises.SList a) | v == f}","col":10,"ident":"f","row":104},"15":{"ann":"GHC.Types.Int","col":15,"ident":"lq_anf$##7205759403793234521","row":104},"19":{"ann":"a","col":19,"ident":"lq_anf$##7205759403793234530","row":104},"22":{"ann":"{v : (LHExercises.SList a) | v == b\n                             && size v == size f + 1}","col":22,"ident":"b","row":104},"31":{"ann":"{v : (LHExercises.SList a) | v == acc}","col":31,"ident":"acc","row":104},"5":{"ann":"{v : GHC.Types.Int | v == size f\n                     && v >= 0}","col":5,"ident":"lq_anf$##7205759403793234519","row":104}},"105":{"17":{"ann":"a","col":17,"ident":"lq_anf$##7205759403793234524","row":105},"20":{"ann":"{v : (LHExercises.SList a) | v == f}","col":20,"ident":"f","row":105},"29":{"ann":"(LHExercises.SList a)","col":29,"ident":"lq_anf$##7205759403793234529","row":105},"33":{"ann":"{v : (LHExercises.SList a) | size v == size f - 1}","col":33,"ident":"lq_anf$##7205759403793234525","row":105},"37":{"ann":"{v : (LHExercises.SList a) | v == f}","col":37,"ident":"f","row":105},"40":{"ann":"{v : (LHExercises.SList a) | size v == size b - 1}","col":40,"ident":"lq_anf$##7205759403793234526","row":105},"44":{"ann":"{v : (LHExercises.SList a) | v == b\n                             && size v == size f + 1}","col":44,"ident":"b","row":105},"47":{"ann":"{v : (LHExercises.SList a) | size v == size acc + 1}","col":47,"ident":"lq_anf$##7205759403793234528","row":105},"48":{"ann":"a","col":48,"ident":"lq_anf$##7205759403793234527","row":105},"51":{"ann":"{v : (LHExercises.SList a) | v == b\n                             && size v == size f + 1}","col":51,"ident":"b","row":105},"60":{"ann":"{v : (LHExercises.SList a) | v == acc}","col":60,"ident":"acc","row":105}},"111":{"1":{"ann":"forall a .\nx1:(LHExercises.Queue a) -> {mq : (GHC.Maybe.Maybe {VV : (LHExercises.Queue a) | qsize VV == qsize x1 - 1}) | qsize x1 > 0 => isJust mq}","col":1,"ident":"LHExercises.remove","row":111},"8":{"ann":"(LHExercises.Queue a)","col":8,"ident":"qi","row":111}},"112":{"10":{"ann":"{v : (LHExercises.SList a) | v == f}","col":10,"ident":"f","row":112},"15":{"ann":"GHC.Types.Int","col":15,"ident":"lq_anf$##7205759403793234541","row":112},"20":{"ann":"{v : GHC.Types.Int | v == size b\n                     && v >= 0}","col":20,"ident":"lq_anf$##7205759403793234543","row":112},"25":{"ann":"{v : (LHExercises.SList a) | v == b\n                             && size v <= size f}","col":25,"ident":"b","row":112},"30":{"ann":"GHC.Types.Int","col":30,"ident":"lq_anf$##7205759403793234545","row":112},"34":{"ann":"{VV : forall a .\n      {v : (GHC.Maybe.Maybe a) | not (isJust v)} | VV == Nothing}","col":34,"ident":"_","row":112},"5":{"ann":"{v : GHC.Types.Int | v == size f\n                     && v >= 0}","col":5,"ident":"lq_anf$##7205759403793234539","row":112}},"113":{"17":{"ann":"{VV : forall a .\n      x1:a -> {v : (GHC.Maybe.Maybe a) | isJust v\n                                         && fromJust v == x1\n                                         && lqdc##$select v == x1} | VV == Just}","col":17,"ident":"GHC.Maybe.Just","row":113},"22":{"ann":"(LHExercises.Queue a)","col":22,"ident":"lq_anf$##7205759403793234550","row":113},"29":{"ann":"{v : (LHExercises.SList a) | size v == size f - 1}","col":29,"ident":"lq_anf$##7205759403793234549","row":113},"33":{"ann":"{v : (LHExercises.SList a) | v == f}","col":33,"ident":"f","row":113},"36":{"ann":"{v : (LHExercises.SList a) | v == b\n                             && size v <= size f}","col":36,"ident":"b","row":113}},"118":{"1":{"ann":"(GHC.Maybe.Maybe (LHExercises.Queue GHC.Num.Integer.Integer))","col":1,"ident":"LHExercises.okRemove","row":118},"19":{"ann":"{v : (LHExercises.Queue GHC.Num.Integer.Integer) | v == example2Q\n                                                   && qsize v == 2}","col":19,"ident":"LHExercises.example2Q","row":118}},"120":{"1":{"ann":"forall a . (GHC.Maybe.Maybe (LHExercises.Queue a))","col":1,"ident":"LHExercises.badRemove","row":120},"20":{"ann":"{VV : forall a .\n      {v : (LHExercises.Queue a) | qsize v == 0} | VV == example0Q}","col":20,"ident":"_","row":120}},"123":{"1":{"ann":"forall a . {VV : (LHExercises.Queue a) | qsize VV == 0}","col":1,"ident":"LHExercises.emp","row":123},"13":{"ann":"{VV : forall a .\n      {v : (LHExercises.SList a) | size v == 0} | VV == nil}","col":13,"ident":"_","row":123},"9":{"ann":"{VV : forall a .\n      {v : (LHExercises.SList a) | size v == 0} | VV == nil}","col":9,"ident":"_","row":123}},"126":{"1":{"ann":"{VV : (LHExercises.Queue GHC.Num.Integer.Integer) | qsize VV == 2}","col":1,"ident":"LHExercises.example2Q","row":126},"15":{"ann":"(LHExercises.SList GHC.Num.Integer.Integer)","col":15,"ident":"lq_anf$##7205759403793234504","row":126},"16":{"ann":"{v : GHC.Num.Integer.Integer | v == 1}","col":16,"ident":"lq_anf$##7205759403793234500","row":126},"25":{"ann":"(LHExercises.SList GHC.Num.Integer.Integer)","col":25,"ident":"lq_anf$##7205759403793234503","row":126},"26":{"ann":"{v : GHC.Num.Integer.Integer | v == 2}","col":26,"ident":"lq_anf$##7205759403793234501","row":126},"35":{"ann":"{VV : forall a .\n      {v : (LHExercises.SList a) | size v == 0} | VV == nil}","col":35,"ident":"_","row":126},"41":{"ann":"{VV : forall a .\n      {v : (LHExercises.SList a) | size v == 0} | VV == nil}","col":41,"ident":"_","row":126}},"129":{"1":{"ann":"forall a . {VV : (LHExercises.Queue a) | qsize VV == 0}","col":1,"ident":"LHExercises.example0Q","row":129},"15":{"ann":"{VV : forall a .\n      {v : (LHExercises.SList a) | size v == 0} | VV == nil}","col":15,"ident":"_","row":129},"19":{"ann":"{VV : forall a .\n      {v : (LHExercises.SList a) | size v == 0} | VV == nil}","col":19,"ident":"_","row":129}},"40":{"1":{"ann":"forall a . x1:[a] -> {VV : GHC.Types.Int | VV == realSize x1}","col":1,"ident":"LHExercises.realSize","row":40},"19":{"ann":"{v : GHC.Prim.Int# | v == 0}","col":19,"ident":"lq_anf$##7205759403793234484","row":40}},"41":{"19":{"ann":"GHC.Types.Int","col":19,"ident":"lq_anf$##7205759403793234486","row":41},"23":{"ann":"{v : GHC.Types.Int | v == realSize xs}","col":23,"ident":"lq_anf$##7205759403793234487","row":41},"32":{"ann":"{v : [a] | v == xs\n           && len v >= 0}","col":32,"ident":"xs","row":41}},"59":{"1":{"ann":"forall a . {VV : (LHExercises.SList a) | size VV == 0}","col":1,"ident":"LHExercises.nil","row":59},"23":{"ann":"GHC.Types.Int","col":23,"ident":"lq_anf$##7205759403793234489","row":59},"25":{"ann":"{VV : forall a <p :: a a -> Bool>.\n      {v : [a]<\\x3 VV -> {VV : a<p x3> | true}> | len v == 0\n                                                  && realSize v == 0} | VV == []}","col":25,"ident":"_","row":59}},"63":{"1":{"ann":"forall a .\na -> x2:(LHExercises.SList a) -> {VV : (LHExercises.SList a) | size VV == size x2 + 1}","col":1,"ident":"LHExercises.cons","row":63},"20":{"ann":"{VV : forall a .\n      x1:{v : GHC.Types.Int | v >= 0} -> x2:{v : [a] | realSize v == x1} -> {v : (LHExercises.SList a) | elems v == x2\n                                                                                                         && size v == x1} | VV == SL}","col":20,"ident":"LHExercises.SL","row":63},"23":{"ann":"GHC.Types.Int","col":23,"ident":"lq_anf$##7205759403793234498","row":63},"24":{"ann":"{v : GHC.Types.Int | v == n\n                     && v >= 0}","col":24,"ident":"n","row":63},"26":{"ann":"GHC.Types.Int","col":26,"ident":"lq_anf$##7205759403793234497","row":63},"29":{"ann":"{v : [a] | head v == x\n           && len v == 1 + len xs\n           && realSize v == 1 + realSize xs\n           && tail v == xs}","col":29,"ident":"lq_anf$##7205759403793234499","row":63},"30":{"ann":"{VV : a | VV == x}","col":30,"ident":"x","row":63},"32":{"ann":"{v : [a] | v == xs\n           && realSize v == n\n           && len v >= 0}","col":32,"ident":"xs","row":63},"6":{"ann":"a","col":6,"ident":"x","row":63}},"68":{"1":{"ann":"forall a .\nx1:{VV : (LHExercises.SList a) | size VV > 0} -> {VV : (LHExercises.SList a) | size VV == size x1 - 1}","col":1,"ident":"LHExercises.tl","row":68},"20":{"ann":"{VV : forall a .\n      x1:{v : GHC.Types.Int | v >= 0} -> x2:{v : [a] | realSize v == x1} -> {v : (LHExercises.SList a) | elems v == x2\n                                                                                                         && size v == x1} | VV == SL}","col":20,"ident":"LHExercises.SL","row":68},"23":{"ann":"GHC.Types.Int","col":23,"ident":"lq_anf$##7205759403793234513","row":68},"24":{"ann":"{v : GHC.Types.Int | v == n\n                     && v >= 0}","col":24,"ident":"n","row":68},"26":{"ann":"GHC.Types.Int","col":26,"ident":"lq_anf$##7205759403793234512","row":68},"29":{"ann":"{v : [a] | v == xs\n           && len v >= 0}","col":29,"ident":"xs","row":68}},"71":{"1":{"ann":"forall a . {VV : (LHExercises.SList a) | size VV > 0} -> a","col":1,"ident":"LHExercises.hd","row":71},"20":{"ann":"{VV : a | VV == x}","col":20,"ident":"x","row":71}},"88":{"1":{"ann":"forall a .\nx1:(LHExercises.Queue a) -> {VV : GHC.Types.Int | VV == qsize x1}","col":1,"ident":"LHExercises.qsize","row":88},"17":{"ann":"{v : GHC.Types.Int | v == size f\n                     && v >= 0}","col":17,"ident":"lq_anf$##7205759403793234553","row":88},"22":{"ann":"{v : (LHExercises.SList a) | v == f}","col":22,"ident":"f","row":88},"26":{"ann":"{v : GHC.Types.Int | v == size b\n                     && v >= 0}","col":26,"ident":"lq_anf$##7205759403793234554","row":88},"31":{"ann":"{v : (LHExercises.SList a) | v == b\n                             && size v <= size f}","col":31,"ident":"b","row":88}},"98":{"1":{"ann":"forall a .\nx1:(LHExercises.SList a) -> x2:{VV : (LHExercises.SList a) | size VV <= size x1 + 1} -> {VV : (LHExercises.Queue a) | qsize VV == size x1 + size x2}","col":1,"ident":"LHExercises.makeq","row":98},"7":{"ann":"(LHExercises.SList a)","col":7,"ident":"f","row":98},"9":{"ann":"{VV : (LHExercises.SList a) | size VV <= size f + 1}","col":9,"ident":"b","row":98}},"99":{"10":{"ann":"{v : (LHExercises.SList a) | v == b\n                             && size v <= size f + 1}","col":10,"ident":"b","row":99},"15":{"ann":"{v : GHC.Types.Int | v == size f\n                     && v >= 0}","col":15,"ident":"lq_anf$##7205759403793234532","row":99},"20":{"ann":"{v : (LHExercises.SList a) | v == f}","col":20,"ident":"f","row":99},"24":{"ann":"{VV : forall a .\n      x1:(LHExercises.SList a) -> x2:{v : (LHExercises.SList a) | size v <= size x1} -> {v : (LHExercises.Queue a) | back v == x2\n                                                                                                                     && front v == x1\n                                                                                                                     && qsize v == size x1 + size x2} | VV == Q}","col":24,"ident":"LHExercises.Q","row":99},"26":{"ann":"{v : (LHExercises.SList a) | v == f}","col":26,"ident":"f","row":99},"28":{"ann":"{v : (LHExercises.SList a) | v == b\n                             && size v <= size f + 1}","col":28,"ident":"b","row":99},"5":{"ann":"{v : GHC.Types.Int | v == size b\n                     && v >= 0}","col":5,"ident":"lq_anf$##7205759403793234531","row":99}}}}